arteria/__init__.py
arteria/version.py
tests/__init__.py
tests/test_sample.py
arteria_python-0.0.1.dist-info/METADATA
arteria_python-0.0.1.dist-info/WHEEL
arteria_python-0.0.1.dist-info/top_level.txt
arteria_python-0.0.1.dist-info/RECORD
