Metadata-Version: 2.1
Name: arteria-python
Version: 0.0.1
Home-page: https://github.com/cuenca-mx/arteria-python
Author: Arteria
Author-email: dev@arteria.io
Classifier: Programming Language :: Python :: 3
Classifier: Programming Language :: Python :: 3.6
Classifier: Programming Language :: Python :: 3.7
Classifier: Programming Language :: Python :: 3.8
Classifier: License :: OSI Approved :: MIT License
Classifier: Operating System :: OS Independent
Requires-Python: >=3.6
Requires-Dist: cuenca (>=0.14.1")
